simplejnius/__init__.py
simplejnius/guava/__init__.py
simplejnius/guava/jclass/__init__.py
simplejnius/guava/jclass/futures.py
simplejnius/guava/jinterface/__init__.py
simplejnius/guava/jinterface/asyncfunction.py
simplejnius/guava/jinterface/function.py
simplejnius/guava/jinterface/futurecallback.py
simplejnius/reactivestreams/__init__.py
simplejnius/reactivestreams/jinterface/__init__.py
simplejnius/reactivestreams/jinterface/subscriber.py
simplejnius-0.2.0.dist-info/LICENSE
simplejnius-0.2.0.dist-info/METADATA
simplejnius-0.2.0.dist-info/WHEEL
simplejnius-0.2.0.dist-info/RECORD
